openoligo/__init__.py
openoligo/api/__init__.py
openoligo/api/db.py
openoligo/api/helpers.py
openoligo/api/models.py
openoligo/hal/__init__.py
openoligo/hal/board.py
openoligo/hal/devices.py
openoligo/hal/gpio.py
openoligo/hal/instrument.py
openoligo/hal/platform.py
openoligo/hal/types.py
openoligo/hil/__init__.py
openoligo/hil/board.py
openoligo/protocols/__init__.py
openoligo/protocols/dna_synthesis.py
openoligo/scripts/__init__.py
openoligo/scripts/hil.py
openoligo/scripts/runner.py
openoligo/scripts/server.py
openoligo/seq.py
openoligo/steps/__init__.py
openoligo/steps/flow.py
openoligo/steps/types.py
openoligo/utils/__init__.py
openoligo/utils/logger.py
openoligo/utils/sim.py
openoligo/utils/singleton.py
openoligo/utils/wait.py
openoligo-0.1.7.dist-info/LICENSE
openoligo-0.1.7.dist-info/METADATA
openoligo-0.1.7.dist-info/WHEEL
openoligo-0.1.7.dist-info/entry_points.txt
openoligo-0.1.7.dist-info/RECORD
