Metadata-Version: 2.1
Name: openoligo
Version: 0.1.7
Summary: An open-source platform for programmatically interacting with and managing Nucleic acid sequences synthesis processes.
License: Apache-2.0
Keywords: DNA,synthesis,genetics,open-source
Author: Satyam Tiwary
Author-email: satyam@technoculture.io
Requires-Python: >=3.9,<4.0
Classifier: License :: OSI Approved :: Apache Software License
Classifier: Programming Language :: Python :: 3
Classifier: Programming Language :: Python :: 3.9
Classifier: Programming Language :: Python :: 3.10
Classifier: Programming Language :: Python :: 3.11
Provides-Extra: bb
Provides-Extra: rpi
Requires-Dist: Adafruit_BBIO (>=1.2.0,<2.0.0) ; extra == "bb"
Requires-Dist: RPi.GPIO (>=0.7.1,<0.8.0) ; extra == "rpi"
Requires-Dist: aerich (>=0.7.1,<0.8.0)
Requires-Dist: anyio (>=3.7.0,<4.0.0)
Requires-Dist: fastapi (>=0.98.0,<0.99.0)
Requires-Dist: httpx (>=0.24.1,<0.25.0)
Requires-Dist: pdocs (>=1.2.0,<2.0.0)
Requires-Dist: python-dotenv (>=1.0.0,<2.0.0)
Requires-Dist: rich (>=13.4.2,<14.0.0)
Requires-Dist: sh (>=2.0.4,<3.0.0)
Requires-Dist: tortoise-orm (>=0.18.1,<0.19.0)
Requires-Dist: tqdm (>=4.65.0,<5.0.0)
Requires-Dist: types-tqdm (>=4.65.0.1,<5.0.0.0)
Requires-Dist: uvicorn (>=0.22.0,<0.23.0)
